vectorgrep/__init__.py
vectorgrep/multiscanner.py
vectorgrep/scanner.py
vectorgrep/utils.py
vectorgrep/lib/__init__.py
vectorgrep/lib/libhs.so.5.4.12
vectorgrep/lib/libvectorgrep.so
vectorgrep/lib/libzstd.so.1.5.7
vectorgrep/lib/c/vectorgrep.c
vectorgrep/lib/c/vectorgrep.h
vectorgrep-1.2.0.dist-info/licenses/COPYING
vectorgrep-1.2.0.dist-info/licenses/LICENSE
vectorgrep-1.2.0.dist-info/METADATA
vectorgrep-1.2.0.dist-info/WHEEL
vectorgrep-1.2.0.dist-info/entry_points.txt
vectorgrep-1.2.0.dist-info/top_level.txt
vectorgrep-1.2.0.dist-info/RECORD
