Metadata-Version: 2.4
Name: vectorgrep
Version: 1.2.0
Summary: Utilities for rapid text file processing using Vectorscan/Hyperscan in Python
Author: David Fritz
License: MIT
Project-URL: Home, https://github.com/pyranha-labs/vectorgrep
Project-URL: Changelog, https://github.com/pyranha-labs/vectorgrep/releases
Project-URL: Issues, https://github.com/pyranha-labs/vectorgrep/issues
Keywords: regex,logs,hyperscan,vectorscan
Platform: Linux
Classifier: Development Status :: 5 - Production/Stable
Classifier: Intended Audience :: Developers
Classifier: Intended Audience :: Science/Research
Classifier: License :: OSI Approved :: MIT License
Classifier: Programming Language :: Python
Classifier: Programming Language :: Python :: 3
Classifier: Programming Language :: Python :: 3 :: Only
Classifier: Programming Language :: Python :: 3.10
Classifier: Programming Language :: Python :: 3.11
Classifier: Topic :: Software Development
Classifier: Topic :: Scientific/Engineering
Classifier: Typing :: Typed
Classifier: Operating System :: POSIX :: Linux
Requires-Python: >=3.10
License-File: LICENSE
License-File: COPYING
Dynamic: license-file
